axi4-lite/axi4_lite.v
module axi_write_logic(
	input axi_clk,
	input rstn, //axi is reset low

    //write logic
	input [1:0] write_addr,
	input write_addr_valid,
	output reg write_addr_ready,

	input [31:0] write_data,
	input write_data_valid,
	output reg write_data_ready,

    input write_resp_ready,
    output reg write_resp_valid,
    output [1:0] write_resp,

    //read logic
    input [1:0] read_addr_i,
    input read_addr_valid_i,
    output reg read_addr_ready_o,

    output [31:0] read_data_o,
    output read_data_valid_o,
    input read_data_ready_i,
    output [1:0] read_resp_o,

    output [31:0] data_out, //data output to external logic
    output [1:0] addr_out,  //address output to external logic
    output data_valid,		//signal indicating output data and address are valid

    /* we don't need valid/ready signal here, axi4-lite would be used by fifo or ram */
    output [1:0] read_addr_to_user_o,
    output reg read_addr_valid_to_user_o,

    input read_data_user_valid_i,
    input [31:0] read_data_from_user_i
);

//flip flops for latching data, addr is 4 bytes aligned
reg [31:0] data_latch;
reg [1:0] addr_latch;
reg [1:0] addr_latch_delay;
reg data_done;
reg addr_done;

reg [31:0] read_data_latch;
reg [1:0] read_addr_latch;
reg read_data_latched;

assign data_out = data_latch;
assign addr_out = addr_latch;
/* this signal only keep assert for one clock, this could cause problem */
assign data_valid = data_done & addr_done;

assign read_addr_to_user_o = read_addr_latch;
assign read_data_o = read_data_latch;
assign read_data_valid_o = read_data_latched;

always@(posedge axi_clk)
begin
    addr_latch_delay <= addr_latch;
end

/* write address handshake*/
always@(posedge axi_clk)
begin
    if(~rstn | (write_addr_valid & write_addr_ready))
        write_addr_ready <= 0;
    else
        write_addr_ready <= 1;
end

/* write data handshake*/
always@(posedge axi_clk)
begin
    if(~rstn | (write_data_valid & write_data_ready))
        write_data_ready <= 0;
    else
        write_data_ready <= 1;
end

always@(posedge axi_clk)
begin
    if(~rstn) begin
        data_latch <= 32'd0;
        addr_latch <= 2'd0;
    end else begin
        if(write_data_valid & write_data_ready)
            data_latch <= write_data;

        if(write_addr_valid & write_addr_ready);
            addr_latch <= write_addr;
    end
end

always@(posedge axi_clk)
begin
    if(~rstn | (data_done & addr_done)) begin
        data_done <= 1'd0;
        addr_done <= 1'd0;
    end else begin
        if(write_data_valid & write_data_ready)
            data_done <= 1'd1;
        if(write_addr_valid & write_addr_ready)
            addr_done <= 1'd1;
    end
end

assign write_resp = 2'd0; // always indicate OKAY status for write
always@(posedge axi_clk)
begin
    if(~rstn | (write_resp_ready & write_resp_valid))
        write_resp_valid <= 1'd0;
    else if(data_done & addr_done)
        write_resp_valid <= 1'd1;
end

//read logic start here.
always@(posedge axi_clk)
begin
    if(~rstn | (read_addr_valid_i & read_addr_ready_o))
        read_addr_ready_o <= 0;
    else
        read_addr_ready_o <= 1;
end

always@(posedge axi_clk)
begin
    if(~rstn) begin
        read_addr_latch <= 2'd0 ;
        read_addr_valid_to_user_o <= 1'd0;
    end else if(read_addr_valid_i & read_addr_ready_o) begin
        read_addr_latch <= read_addr_i;
        read_addr_valid_to_user_o <= 1'd1; // valid only keep high for 1 clock.
    end else begin
        read_addr_latch <= 2'd0 ;
        read_addr_valid_to_user_o <= 1'd0;
    end
end

always@(posedge axi_clk)
begin
    if(~rstn) begin
        read_data_latch <= 32'd0;
        read_data_latched <= 1'd0;
    end else if(read_data_user_valid_i) begin
        read_data_latch <= read_data_from_user_i;
        read_data_latched <= 1'd1;
    end else if(read_data_latched & read_data_ready_i) begin
        read_data_latch <= 32'd0;
        read_data_latched <= 1'd0;
    end
end

endmodule

axi4-lite/axi_mapped_registers.v
module axi_mapped_registers(
    input axi_clk,
    input axi_rstn,
    
    input [31:0] axi_write_data,
    input write_data_valid,
    output write_data_ready,
    
    input [1:0] axi_write_addr,
    input write_addr_valid,
    output write_addr_ready,
    
    output [1:0] axi_write_resp,
    input write_resp_ready,
    output write_resp_valid,
    
    input [1:0] axi_read_addr_i,
    input read_addr_valid_i,
    output read_addr_ready_o,

    output[31:0] axi_read_data_o,
    output read_data_valid_o,
    input read_data_ready_i,
    output [1:0] read_resp_o
);

reg[31:0] regs[3:0];
wire[31:0] write_data;
wire[1:0] write_addr;
wire write_en;
wire[31:0] debug_d0;
wire[31:0] debug_d1;
wire[31:0] debug_d2;
wire[31:0] debug_d3;

//read logic
wire read_en;
wire[1:0] read_addr;
reg[31:0] read_data;
reg read_data_en;

assign debug_d0 = regs[0];
assign debug_d1 = regs[1];
assign debug_d2 = regs[2];
assign debug_d3 = regs[3];

axi_write_logic axi_inst(
    .axi_clk(axi_clk),
    .rstn(axi_rstn), //axi is reset low

    .write_data(axi_write_data),
    .write_data_valid(write_data_valid),
    .write_data_ready(write_data_ready),

    .write_addr(axi_write_addr),
    .write_addr_valid(write_addr_valid),
    .write_addr_ready(write_addr_ready),

    .write_resp_ready(write_resp_ready),
    .write_resp_valid(write_resp_valid),
    .write_resp(axi_write_resp),

    .read_addr_i(axi_read_addr_i),
    .read_addr_valid_i(read_addr_valid_i),
    .read_addr_ready_o(read_addr_ready_o),

    .read_data_o(axi_read_data_o),
    .read_data_valid_o(read_data_valid_o),
    .read_data_ready_i(read_data_ready_i),
    .read_resp_o(read_resp_o),

    .data_out(write_data), //data output to external logic
    .addr_out(write_addr), //address output to external logic
    .data_valid(write_en),

    .read_addr_to_user_o(read_addr),
    .read_addr_valid_to_user_o(read_en),

    .read_data_user_valid_i(read_data_en),
    .read_data_from_user_i(read_data)
);


integer i;
always@(posedge axi_clk)
begin
    if(~axi_rstn) begin
        for(i=0;i<4;i++)
            regs[i] <= 32'd0;
    end else if(write_en) begin
        regs[write_addr] <= write_data;
    end else if(read_en) begin
        read_data <= regs[read_addr];
        read_data_en <= 1'd1;
    end else begin
        read_data <= 32'd0;
        read_data_en <= 1'd0;
    end
end

endmodule

axi4-lite/axi4_tb.v
`timescale 1ns/1ps

`define CLOCK_PERIOD 10

module axi4_testbench();
    reg clk = 0;
    reg rst = 0;

    // Generate 100 MHz clock
    always #(`CLOCK_PERIOD/2) clk = ~clk;

    reg [31:0] write_data = 32'd0;
    reg write_data_valid = 0;
    wire write_data_ready;

    reg [1:0] write_addr = 2'd0;
    reg write_addr_valid = 0;
    wire write_addr_ready;

    wire [1:0] write_resp;
    wire write_resp_valid;
    reg write_resp_ready = 0; 

    reg [1:0] read_addr;
    reg read_addr_valid;
    wire read_addr_ready;

    wire [31:0] read_data;
    wire read_data_valid;
    reg read_data_ready;
    wire [1:0] read_resp;

    axi_mapped_registers axi_periph(
        .axi_clk(clk),
        .axi_rstn(rst),
        
        .axi_write_data(write_data),
        .write_data_valid(write_data_valid),
        .write_data_ready(write_data_ready),
        
        .axi_write_addr(write_addr),
        .write_addr_valid(write_addr_valid),
        .write_addr_ready(write_addr_ready),
        
        .axi_write_resp(write_resp),
        .write_resp_ready(write_resp_ready),
        .write_resp_valid(write_resp_valid),

        .axi_read_addr_i(read_addr),
        .read_addr_valid_i(read_addr_valid),
        .read_addr_ready_o(read_addr_ready),

        .axi_read_data_o(read_data),
        .read_data_valid_o(read_data_valid),
        .read_data_ready_i(read_data_ready),
        .read_resp_o(read_resp)
   );

    reg done = 0;
    initial begin
        $dumpfile("axi4-lite-tb.vcd");
        $dumpvars(0, axi4_testbench);

        fork
            begin

                $monitor("reg[0] %d\n", axi_periph.regs[0]);
                $monitor("reg[1] %d\n", axi_periph.regs[1]);
                $monitor("reg[2] %d\n", axi_periph.regs[2]);
                $monitor("reg[3] %d\n", axi_periph.regs[3]);
                rst = 0;
                write_data_valid = 0;
                write_addr_valid = 0;
                write_resp_ready = 0;
                read_addr = 0;
                read_addr_valid = 0;
                read_data_ready = 1;
                repeat(2) @(posedge clk);
                rst = 1;
                repeat(5) @(posedge clk);
                write_data = 32'd1234;
                #2; //setup time
                write_data_valid = 1;
                @(posedge clk);
                #2; //hold time
                write_data_valid = 0;

                repeat(2) @(posedge clk);
                write_addr = 2'd3;
                #2; //setup time
                write_addr_valid = 1;
                @(posedge clk);
                #2; //hold time
                write_addr_valid = 0;

                $display("start read");
                @(posedge clk);
                #2;read_addr = 2'd0;
                read_addr_valid = 1;
                @(posedge clk);
                #2;read_addr_valid = 0;
                repeat(5)@(posedge clk);

                #2;read_addr = 2'd3;
                read_addr_valid = 1;
                @(posedge clk);
                #2;read_addr_valid = 0;
                repeat(5)@(posedge clk);
                
            end
            begin
                repeat (25000) @(posedge clk);
                if (!done) begin
                    $display("Failure: timing out");
                    $finish();
                end
            end
        join
    end

endmodule

axi4-lite/axi4-lite-tb.vcd
$date
	Tue Dec 27 09:21:11 2022
$end
$version
	Icarus Verilog
$end
$timescale
	1ps
$end
$scope module axi4_testbench $end
$var wire 2 ! read_resp [1:0] $end
$var wire 2 " write_resp [1:0] $end
$var wire 1 # write_resp_valid $end
$var wire 1 $ write_data_ready $end
$var wire 1 % write_addr_ready $end
$var wire 1 & read_data_valid $end
$var wire 32 ' read_data [31:0] $end
$var wire 1 ( read_addr_ready $end
$var reg 1 ) clk $end
$var reg 1 * done $end
$var reg 2 + read_addr [1:0] $end
$var reg 1 , read_addr_valid $end
$var reg 1 - read_data_ready $end
$var reg 1 . rst $end
$var reg 2 / write_addr [1:0] $end
$var reg 1 0 write_addr_valid $end
$var reg 32 1 write_data [31:0] $end
$var reg 1 2 write_data_valid $end
$var reg 1 3 write_resp_ready $end
$scope module axi_periph $end
$var wire 1 ) axi_clk $end
$var wire 2 4 axi_read_addr_i [1:0] $end
$var wire 1 . axi_rstn $end
$var wire 2 5 axi_write_addr [1:0] $end
$var wire 32 6 axi_write_data [31:0] $end
$var wire 2 7 axi_write_resp [1:0] $end
$var wire 32 8 debug_d0 [31:0] $end
$var wire 32 9 debug_d1 [31:0] $end
$var wire 32 : debug_d2 [31:0] $end
$var wire 32 ; debug_d3 [31:0] $end
$var wire 1 , read_addr_valid_i $end
$var wire 1 - read_data_ready_i $end
$var wire 2 < read_resp_o [1:0] $end
$var wire 1 0 write_addr_valid $end
$var wire 1 2 write_data_valid $end
$var wire 1 3 write_resp_ready $end
$var wire 1 # write_resp_valid $end
$var wire 1 = write_en $end
$var wire 1 $ write_data_ready $end
$var wire 32 > write_data [31:0] $end
$var wire 1 % write_addr_ready $end
$var wire 2 ? write_addr [1:0] $end
$var wire 1 @ read_en $end
$var wire 1 & read_data_valid_o $end
$var wire 1 ( read_addr_ready_o $end
$var wire 2 A read_addr [1:0] $end
$var wire 32 B axi_read_data_o [31:0] $end
$var reg 32 C read_data [31:0] $end
$var reg 1 D read_data_en $end
$var integer 32 E i [31:0] $end
$scope module axi_inst $end
$var wire 2 F addr_out [1:0] $end
$var wire 1 ) axi_clk $end
$var wire 32 G data_out [31:0] $end
$var wire 1 = data_valid $end
$var wire 2 H read_addr_i [1:0] $end
$var wire 2 I read_addr_to_user_o [1:0] $end
$var wire 1 , read_addr_valid_i $end
$var wire 32 J read_data_from_user_i [31:0] $end
$var wire 32 K read_data_o [31:0] $end
$var wire 1 - read_data_ready_i $end
$var wire 1 D read_data_user_valid_i $end
$var wire 1 & read_data_valid_o $end
$var wire 2 L read_resp_o [1:0] $end
$var wire 1 . rstn $end
$var wire 2 M write_addr [1:0] $end
$var wire 1 0 write_addr_valid $end
$var wire 32 N write_data [31:0] $end
$var wire 1 2 write_data_valid $end
$var wire 2 O write_resp [1:0] $end
$var wire 1 3 write_resp_ready $end
$var reg 1 P addr_done $end
$var reg 2 Q addr_latch [1:0] $end
$var reg 2 R addr_latch_delay [1:0] $end
$var reg 1 S data_done $end
$var reg 32 T data_latch [31:0] $end
$var reg 2 U read_addr_latch [1:0] $end
$var reg 1 ( read_addr_ready_o $end
$var reg 1 @ read_addr_valid_to_user_o $end
$var reg 32 V read_data_latch [31:0] $end
$var reg 1 W read_data_latched $end
$var reg 1 % write_addr_ready $end
$var reg 1 $ write_data_ready $end
$var reg 1 # write_resp_valid $end
$upscope $end
$upscope $end
$upscope $end
$enddefinitions $end
#0
$dumpvars
xW
bx V
bx U
bx T
xS
bx R
bx Q
xP
b0 O
b0 N
b0 M
bz L
bx K
bx J
bx I
b0 H
bx G
bx F
bx E
xD
bx C
bx B
bx A
x@
bx ?
bx >
x=
bz <
bx ;
bx :
bx 9
bx 8
b0 7
b0 6
b0 5
b0 4
03
02
b0 1
00
b0 /
0.
1-
0,
b0 +
0*
0)
x(
bx '
x&
x%
x$
x#
b0 "
bz !
$end
#5000
0=
0%
0$
b0 ?
b0 F
b0 Q
b0 >
b0 G
b0 T
0P
0S
0#
0(
0@
b0 A
b0 I
b0 U
0&
0W
b0 '
b0 B
b0 K
b0 V
b0 ;
b0 :
b0 9
b0 8
b100 E
1)
#10000
0)
#15000
b0 R
1.
b100 E
1)
#20000
0)
#25000
1%
1$
1(
0D
b0 C
b0 J
1)
#30000
0)
#35000
1)
#40000
0)
#45000
1)
#50000
0)
#55000
1)
#60000
0)
#65000
b10011010010 1
b10011010010 6
b10011010010 N
1)
#67000
12
#70000
0)
#75000
1S
b10011010010 >
b10011010010 G
b10011010010 T
0$
1)
#77000
02
#80000
0)
#85000
1$
1)
#90000
0)
#95000
b11 /
b11 5
b11 M
1)
#97000
10
#100000
0)
#105000
1=
0%
b11 ?
b11 F
b11 Q
1P
1)
#107000
00
#110000
0)
#115000
0=
b10011010010 ;
1#
0P
0S
1%
b11 R
1)
#117000
1,
#120000
0)
#125000
0(
1@
1)
#127000
0,
#130000
0)
#135000
1D
0@
1(
1)
#140000
0)
#145000
1&
1W
0D
1)
#150000
0)
#155000
0&
0W
1)
#160000
0)
#165000
1)
#170000
0)
#175000
1)
#177000
1,
b11 +
b11 4
b11 H
#180000
0)
#185000
0(
1@
b11 A
b11 I
b11 U
1)
#187000
0,
#190000
0)
#195000
1D
b10011010010 C
b10011010010 J
0@
b0 A
b0 I
b0 U
1(
1)
#200000
0)
#205000
1&
1W
b10011010010 '
b10011010010 B
b10011010010 K
b10011010010 V
0D
b0 C
b0 J
1)
#210000
0)
#215000
0&
0W
b0 '
b0 B
b0 K
b0 V
1)
