handshake/receiver.v
`timescale 1ns/1ns

module receiver #(
    parameter DATA_WIDTH = 8,
    parameter DEPTH = 16, 
    parameter ADDR_WIDTH = $clog2(DEPTH)
) (
    input   clk,
    input   rst,
    output  ready,
    input   ready_test,
    input   valid,
    input   [DATA_WIDTH-1:0] data
);

    /* To receive data, ready_test should also be valid */
    reg [DATA_WIDTH-1:0] mem[0:DEPTH-1];
    reg [ADDR_WIDTH:0] idx; 
    reg [DATA_WIDTH-1:0] debug_reg;
    assign ready = (idx != DEPTH) & ready_test; 

    always@(posedge clk or posedge rst) begin
        if(rst)begin
            idx <= 1'b0;
        end else begin
            if(ready_test & ready & valid) begin
                idx <= idx + 1'b1;
                mem[idx] <= data;
                debug_reg <= data;
            end else begin
                idx <= idx;
                mem[idx] <= mem[idx];
                debug_reg <= debug_reg;
            end
        end
    end 
endmodule

handshake/sender.v
`timescale 1ns/1ns

module sender #(
    parameter DATA_WIDTH = 8,
    parameter DEPTH = 16,
    parameter ADDR_WIDTH = $clog2(DEPTH)
) (
    input clk,
    input rst,
    input ready,
    output valid,
    input valid_test,
    output [DATA_WIDTH-1:0] data
);

    reg [DATA_WIDTH-1:0] mem[0:DEPTH-1];
    reg [ADDR_WIDTH:0] idx; 
    assign valid = (idx != DEPTH) & valid_test; 
    assign data = mem[idx];

    always@(posedge clk or posedge rst) begin
        if(rst)begin
            idx <= 1'b0;
        end else begin
            if(ready & valid & valid_test)
                idx <= idx + 1'b1;
            else
                idx <= idx;
        end
    end
endmodule

handshake/bubble_tb.v
`timescale 1ns/1ns

`define CLK_PERIOD 8
`define WIDTH 8 

module bubble_tb();

    reg clk = 0;
    always #(`CLK_PERIOD/2) clk = ~clk;
    
    wire[`WIDTH-1:0] data_w;
    wire valid_w;
    /* pipe reg */
    reg[`WIDTH-1:0] data_pipe;
    reg valid_pipe;
    reg pipe_cnt;

    reg rst;
    reg ready_test;
    reg valid_test;
    wire pipe_in;
    wire pipe_out;
    wire r_o;

    assign pipe_in = r_o & valid_w;
    assign pipe_out = ready & valid_pipe;
    assign r_o = ready | (~valid_pipe);

    always@(posedge clk or posedge rst) begin
        if(rst) begin
            valid_pipe <= 1'b0;;
        end else begin
            if(r_o) begin
                valid_pipe <= valid_w;
            end
        end
    end

    always@(posedge clk or posedge rst) begin
        if(rst) begin
            data_pipe <= `WIDTH'b0;
        end else begin
            if(r_o & valid_w) begin
                data_pipe <= data_w;
            end
        end
    end

    always@(posedge clk or posedge rst) begin
        if(rst) begin
            pipe_cnt <= 1'b0;
        end else begin
            case({pipe_in, pipe_out})
            2'b10: pipe_cnt <= pipe_cnt + 1;  
            2'b01: pipe_cnt <= pipe_cnt - 1;  
            default: pipe_cnt <= pipe_cnt;
            endcase
        end
    end

    sender # ( 
        .DATA_WIDTH(`WIDTH),
        .DEPTH(16)
    ) send (
        .clk(clk),
        .rst(rst),
        .ready(r_o),
        .valid(valid_w),
        .valid_test(valid_test),
        .data(data_w)
    );

    receiver # ( 
        .DATA_WIDTH(`WIDTH),
        .DEPTH(16)
    ) rec (
        .clk(clk),
        .rst(rst),
        .ready(ready),
        .ready_test(ready_test),
        .valid(valid_pipe),
        .data(data_pipe)
    );

    integer index;
    initial begin
        $readmemh("./data.hex", send.mem);
        for(index=0;index<16;index++)
            $display("%x ", send.mem[index]);

        $dumpfile("bubble_tb.vcd");
        $dumpvars(0, bubble_tb);

        pipe_cnt = 0;
        @(posedge clk);
        rst = 1;
        ready_test = 0;
        valid_test = 0;
        repeat(2) @(posedge clk);
        #1;rst = 0;
        valid_test = 1;
        repeat(4) @(posedge clk);
        #1;ready_test = 1;
        repeat(4) @(posedge clk);
        #1;valid_test = 0;
        repeat(4) @(posedge clk);

        $finish();
    end

endmodule

handshake/bubble_tb.vcd
$date
	Tue Dec 20 15:23:32 2022
$end
$version
	Icarus Verilog
$end
$timescale
	1ns
$end
$scope module bubble_tb $end
$var wire 1 ! pipe_in $end
$var wire 1 " pipe_out $end
$var wire 1 # r_o $end
$var wire 1 $ valid_w $end
$var wire 1 % ready $end
$var wire 8 & data_w [7:0] $end
$var reg 1 ' clk $end
$var reg 8 ( data_pipe [7:0] $end
$var reg 1 ) pipe_cnt $end
$var reg 1 * ready_test $end
$var reg 1 + rst $end
$var reg 1 , valid_pipe $end
$var reg 1 - valid_test $end
$var integer 32 . index [31:0] $end
$scope module rec $end
$var wire 1 ' clk $end
$var wire 8 / data [7:0] $end
$var wire 1 % ready $end
$var wire 1 * ready_test $end
$var wire 1 + rst $end
$var wire 1 , valid $end
$var reg 8 0 debug_reg [7:0] $end
$var reg 5 1 idx [4:0] $end
$upscope $end
$scope module send $end
$var wire 1 ' clk $end
$var wire 8 2 data [7:0] $end
$var wire 1 # ready $end
$var wire 1 + rst $end
$var wire 1 $ valid $end
$var wire 1 - valid_test $end
$var reg 5 3 idx [4:0] $end
$upscope $end
$upscope $end
$enddefinitions $end
#0
$dumpvars
bx 3
bx 2
bx 1
bx 0
bx /
b10000 .
x-
x,
x+
x*
0)
bx (
0'
bx &
x%
x$
x#
x"
x!
$end
#4
1#
b10001 &
b10001 2
b0 3
b0 1
0,
b0 (
b0 /
0!
0"
0$
0%
0-
0*
1+
1'
#8
0'
#12
1'
#16
0'
#20
1'
#21
1!
1$
1-
0+
#24
0'
#28
0!
0#
1)
b10001 (
b10001 /
1,
b100010 &
b100010 2
b1 3
1'
#32
0'
#36
1'
#40
0'
#44
1'
#48
0'
#52
1'
#53
1!
1#
1"
1%
1*
#56
0'
#60
b100010 (
b100010 /
b10001 0
b1 1
b110011 &
b110011 2
b10 3
1'
#64
0'
#68
b1000100 &
b1000100 2
b11 3
b100010 0
b10 1
b110011 (
b110011 /
1'
#72
0'
#76
b1000100 (
b1000100 /
b110011 0
b11 1
b1010101 &
b1010101 2
b100 3
1'
#80
0'
#84
b1100110 &
b1100110 2
b101 3
b1000100 0
b100 1
b1010101 (
b1010101 /
1'
#85
0!
0$
0-
#88
0'
#92
0"
0)
0,
b1010101 0
b101 1
1'
